<?xml version="1.0" encoding="UTF-8"?>
<objects serializationModel="Studio.02.00.00">
	<object class="AudioFile" id="{d7415cb8-0179-4354-a1ed-8e307017b517}">
		<property name="assetPath">
			<value>Snow, Impact, Snowball, Impact, Bushes Snow 01 SND72617 1.wav</value>
		</property>
		<property name="frequencyInKHz">
			<value>96</value>
		</property>
		<property name="channelCount">
			<value>2</value>
		</property>
		<property name="length">
			<value>0.32564583333333336</value>
		</property>
		<relationship name="masterAssetFolder">
			<destination>{3dbd60c1-f6f2-4982-8641-70c5407585f4}</destination>
		</relationship>
	</object>
</objects>
